danish05_watermarkpackage/__init__.py
danish05_watermarkpackage/danish05_module.py
danish05_watermarkpackage-0.1.0.dist-info/licenses/LICENSE
danish05_watermarkpackage-0.1.0.dist-info/WHEEL
danish05_watermarkpackage-0.1.0.dist-info/METADATA
danish05_watermarkpackage-0.1.0.dist-info/RECORD
